orc2pstgrs/__init__.py
orc2pstgrs-0.0.1.dist-info/LICENSE.txt
orc2pstgrs-0.0.1.dist-info/METADATA
orc2pstgrs-0.0.1.dist-info/WHEEL
orc2pstgrs-0.0.1.dist-info/top_level.txt
orc2pstgrs-0.0.1.dist-info/RECORD
