Metadata-Version: 2.1
Name: orc2pstgrs
Version: 0.0.1
Summary: adding number
Home-page: https://github.com/rohitjangirdata/
Author: rohit jangir
Author-email: rohit.jangir.data@gmail.com
License: UNKNOWN
Platform: UNKNOWN
Classifier: Programming Language :: Python :: 3
Classifier: License :: OSI Approved :: MIT License
Classifier: Operating System :: OS Independent
